kpsearch/__init__.py
kpsearch/kpsearch.py
kpsearch-1.0.0.dist-info/LICENSE
kpsearch-1.0.0.dist-info/METADATA
kpsearch-1.0.0.dist-info/WHEEL
kpsearch-1.0.0.dist-info/top_level.txt
kpsearch-1.0.0.dist-info/RECORD
