Metadata-Version: 2.1
Name: kpsearch
Version: 1.0.0
Summary: K-portfolio search
Author-email: Jakob Bach <jakob.bach.ka@gmail.com>
Project-URL: Homepage, https://github.com/Jakob-Bach/Small-Portfolios/tree/master/code/kpsearch_package
Project-URL: Issues, https://github.com/Jakob-Bach/Small-Portfolios/issues
Keywords: portfolio search,portfolios,algorithms,solvers
Classifier: Programming Language :: Python :: 3
Classifier: License :: OSI Approved :: MIT License
Classifier: Operating System :: OS Independent
Requires-Python: >=3.8
License-File: LICENSE
Requires-Dist: mip >=1.13.0
Requires-Dist: pandas >=1.4.2
Requires-Dist: z3-solver >=4.8.17.0
